syndat/__init__.py
syndat/_version.py
syndat/metrics.py
syndat/postprocessing.py
syndat/rct/__init__.py
syndat/rct/metrics_rct.py
syndat/rct/preprocessing_tidy_format.py
syndat/rct/visualization_clinical_trials.py
syndat/scores.py
syndat/visualization.py
syndat-0.13.5.dist-info/METADATA
syndat-0.13.5.dist-info/WHEEL
syndat-0.13.5.dist-info/licenses/LICENSE
syndat-0.13.5.dist-info/RECORD
