Metadata-Version: 2.4
Name: syndat
Version: 0.13.5
Summary: A library for evaluation & visualization of synthetic data.
License: MIT
License-File: LICENSE
Keywords: synthetic-data,data-quality,data-visualization
Author: Tim Adams
Author-email: tim.adams@scai.fraunhofer.de
Requires-Python: >=3.9
Classifier: Development Status :: 3 - Alpha
Classifier: Intended Audience :: Developers
Classifier: License :: OSI Approved :: Apache Software License
Classifier: License :: OSI Approved :: MIT License
Classifier: Programming Language :: Python :: 3
Classifier: Programming Language :: Python :: 3.9
Classifier: Programming Language :: Python :: 3.10
Classifier: Programming Language :: Python :: 3.11
Classifier: Programming Language :: Python :: 3.12
Classifier: Programming Language :: Python :: 3.13
Classifier: Programming Language :: Python :: 3.14
Requires-Dist: matplotlib (>=3.8.2,<4.0.0)
Requires-Dist: numpy (>1.26.2,<3.0.0)
Requires-Dist: pandas (>=2.1.4,<3.0.0)
Requires-Dist: plotnine (>=0.13.6,<0.14.0)
Requires-Dist: scikit-learn (>=1.5.1,<2.0.0)
Requires-Dist: scipy (>=1.11.4,<2.0.0)
Requires-Dist: seaborn (>=0.13.0,<0.14.0)
Requires-Dist: shap (>=0.47.0,<0.48.0)
Project-URL: Documentation, https://github.com/SCAI-BIO/syndat#readme
Project-URL: Homepage, https://github.com/SCAI-BIO/syndat
Project-URL: Repository, https://github.com/SCAI-BIO/syndat
Project-URL: documentation, https://github.com/SCAI-BIO/syndat#readme
Project-URL: source, https://github.com/SCAI-BIO/syndat
Project-URL: tracker, https://github.com/SCAI-BIO/syndat/issues
